liquid.cpython-311-x86_64-linux-gnu.so
liquid_dsp-1.6.0.dist-info/WHEEL
liquid_dsp-1.6.0.dist-info/RECORD
liquid_dsp-1.6.0.dist-info/METADATA
liquid_dsp-1.6.0.dist-info/licenses/LICENSE
lib/libliquidtmp.so
lib/libliquidtmp.so.1
