Metadata-Version: 2.1
Name: liquid-dsp
Version: 1.6.0
Summary: software-defined radio digital signal processing library
Keywords: digital,signal,processing,DSP,software-defined radio,SDR
Author-Email: "Joseph D. Gaeddert" <joseph@liquidsdr.org>
License: Copyright (c) 2007 - 2016 Joseph Gaeddert
Classifier: Development Status :: 4 - Beta
Classifier: Intended Audience :: Developers
Classifier: Topic :: Scientific/Engineering
Classifier: Programming Language :: C
Classifier: Programming Language :: C++
Classifier: Programming Language :: Python :: 3 :: Only
Classifier: License :: OSI Approved :: MIT License
Project-URL: Homepage, https://liquidsdr.org
Project-URL: Documentation, https://liquidsdr.org/doc
Project-URL: Repository, https://github.com/jgaeddert/liquid-dsp
Project-URL: Issues, https://github.com/jgaeddert/liquid-dsp/issues
Project-URL: Changelog, https://github.com/jgaeddert/liquid-dsp/blob/master/CHANGELOG.md
Requires-Python: >=3.7
